sbsecuretunnel/__init__.py
sbsecuretunnel/sb_securetunnel.py
sbsecuretunnel-0.0.3.dist-info/METADATA
sbsecuretunnel-0.0.3.dist-info/WHEEL
sbsecuretunnel-0.0.3.dist-info/top_level.txt
sbsecuretunnel-0.0.3.dist-info/RECORD
