Metadata-Version: 2.1
Name: sbsecuretunnel
Version: 0.0.3
Summary: A wrapper for Smartbear SecureTunnel, to make testing local sites easier in CrossBrowserTesting
Home-page: https://github.com/crossbrowsertesting/sb_securetunnel_py
Author: CrossBrowserTesting
Author-email: info@crossbrowsertesting.com
License: UNKNOWN
Platform: UNKNOWN
Classifier: Programming Language :: Python :: 3
Classifier: License :: OSI Approved :: MIT License
Classifier: Operating System :: OS Independent
Requires-Python: >=3.6.2
Requires-Dist: requests
